simpler_whisper/__init__.py
simpler_whisper/_whisper_cpp.cp310-win_amd64.pyd
simpler_whisper/ggml.dll
simpler_whisper/libopenblas.dll
simpler_whisper/whisper.dll
simpler_whisper/whisper.py
simpler_whisper-0.2.4.post3.dist-info/LICENSE
simpler_whisper-0.2.4.post3.dist-info/METADATA
simpler_whisper-0.2.4.post3.dist-info/WHEEL
simpler_whisper-0.2.4.post3.dist-info/top_level.txt
simpler_whisper-0.2.4.post3.dist-info/RECORD
