Metadata-Version: 2.1
Name: simpler-whisper
Version: 0.2.4.post3
Summary: A simple Python wrapper for whisper.cpp
Author: Roy Shilkrot
Author-email: Roy Shilkrot <roy.shil@gmail.com>
Project-URL: Homepage, https://github.com/locaal-ai/simpler-whisper
Project-URL: Bug Tracker, https://github.com/locaal-ai/simpler-whisper/issues
Classifier: Development Status :: 3 - Alpha
Classifier: Intended Audience :: Developers
Classifier: License :: OSI Approved :: MIT License
Classifier: Operating System :: OS Independent
Classifier: Programming Language :: Python :: 3
Classifier: Programming Language :: Python :: 3.10
Classifier: Programming Language :: Python :: 3.11
Classifier: Programming Language :: Python :: 3.12
Requires-Python: >=3.10
License-File: LICENSE
Requires-Dist: numpy
Provides-Extra: test
Requires-Dist: pytest>=7.0; extra == "test"
Requires-Dist: requests>=2.0.0; extra == "test"
